apibean/intercept/__init__.py
apibean/intercept/brokers/__init__.py
apibean/intercept/brokers/broker.py
apibean/intercept/brokers/builder.py
apibean/intercept/brokers/models.py
apibean/intercept/brokers/dispatchers/__init__.py
apibean/intercept/brokers/dispatchers/abstract.py
apibean/intercept/brokers/dispatchers/fastapi_app.py
apibean/intercept/brokers/interceptors/__init__.py
apibean/intercept/brokers/resolvers/_BaseUpstreamResolver.py
apibean/intercept/brokers/resolvers/_DefaultUpstreamResolver.py
apibean/intercept/brokers/resolvers/_DynamicCodeResolver.py
apibean/intercept/brokers/resolvers/_ResolverChain.py
apibean/intercept/brokers/resolvers/__init__.py
apibean/intercept/examples/ndjson_log_stream.py
apibean/intercept/recipes/__init__.py
apibean/intercept/recipes/dispatchers/__init__.py
apibean/intercept/recipes/dispatchers/_ndjson_log_stream.py
apibean/intercept/recipes/dispatchers/_progress_ndjson_stream.py
apibean/intercept/recipes/interceptors/__init__.py
apibean/intercept/recipes/interceptors/_response_transform.py
apibean/intercept/recipes/interceptors/_response_transform_demo.py
apibean/intercept/recipes/interceptors/_streaming_response_ndjson_enrichment.py
apibean/intercept/recipes/interceptors/_streaming_response_transform.py
apibean/intercept/servers/_EmbeddedAPIServerBase.py
apibean/intercept/servers/_EmbeddedAPIServerDev.py
apibean/intercept/servers/_EmbeddedAPIServerLab.py
apibean/intercept/servers/_ServerStatus.py
apibean/intercept/servers/__init__.py
apibean/intercept/servers/fastapi_server.py
apibean/intercept/servers/fastapi_util.py
apibean/intercept/servers/handlers/_AsgiSender.py
apibean/intercept/servers/handlers/_AsgiSenderAdapter.py
apibean/intercept/servers/handlers/_AsgiSenderStream.py
apibean/intercept/servers/handlers/_HttpxClient.py
apibean/intercept/servers/handlers/_HttpxClientAdapter.py
apibean/intercept/servers/handlers/_HttpxClientStream.py
apibean/intercept/servers/handlers/_TestClient.py
apibean_intercept-0.1.1a5.dist-info/METADATA
apibean_intercept-0.1.1a5.dist-info/WHEEL
apibean_intercept-0.1.1a5.dist-info/top_level.txt
apibean_intercept-0.1.1a5.dist-info/RECORD
