Metadata-Version: 2.4
Name: apibean-intercept
Version: 0.1.1a5
Summary: API interception engine for proxying, extending and observing REST APIs
Requires-Python: <4.0,>=3.9
Requires-Dist: asyncio>=3.4.3
Requires-Dist: fastapi<1.0.0,>=0.114.2
Requires-Dist: httpx>=0.28.1
Requires-Dist: ipython<9.3,>=8.12; python_version < "3.11"
Requires-Dist: ipython>=9.3; python_version >= "3.11"
Requires-Dist: psutil>=7.0.0
Requires-Dist: pyyaml>=6.0.3
Requires-Dist: uvicorn>=0.34.3
